{
  "id": "boolean-conditional-field",
  "name": "Boolean conditional field",
  "srcdoc": "index.html",
  "fieldTypes": ["Boolean"],
  "parameters": {
    "instance": [
      {
        "id": "field",
        "name": "Se questo campo",
        "description": "Esempio: title",
        "type": "Symbol",
        "required": true,
        "default": ""
      },
      {
        "id": "operator",
        "name": "è",
        "description": "Esempio: ==, !=",
        "type": "Symbol",
        "required": true,
        "default": "=="
      },
      {
        "id": "value",
        "name": "a",
        "description": "Esempio: true, 'red'",
        "type": "Symbol",
        "required": true,
        "default": ""
      }
    ]
  }
}